seleniumactions/__init__.py
seleniumactions/actions.py
seleniumactions/conditions.py
seleniumactions/elements.py
seleniumactions/pages.py
selenium_actions-1.0.6.dist-info/LICENSE
selenium_actions-1.0.6.dist-info/METADATA
selenium_actions-1.0.6.dist-info/WHEEL
selenium_actions-1.0.6.dist-info/top_level.txt
selenium_actions-1.0.6.dist-info/RECORD
