Metadata-Version: 2.1
Name: selenium-actions
Version: 1.0.6
Summary: Selenium Actions - Action Based Selenium library - selenium in more accessible way :)
Author-email: Tomasz Majk <tmajk@saskodzi.pl>
License: MIT License
Project-URL: Homepage, https://github.com/bigSAS/selenium-actions
Keywords: selenium,actions,selenium-actions,seleniumactions,saskodzi,omni-selenium
Classifier: License :: OSI Approved :: MIT License
Classifier: Programming Language :: Python :: 3.6
Requires-Python: >=3.6
License-File: LICENSE
Requires-Dist: selenium (>=4.2.0)
